quickstock/__init__.py
quickstock/client.py
quickstock/config.py
quickstock/models.py
quickstock/py.typed
quickstock/core/__init__.py
quickstock/core/cache.py
quickstock/core/connection_pool.py
quickstock/core/data_manager.py
quickstock/core/errors.py
quickstock/core/formatter.py
quickstock/core/scheduler.py
quickstock/providers/__init__.py
quickstock/providers/baostock.py
quickstock/providers/base.py
quickstock/providers/eastmoney.py
quickstock/providers/manager.py
quickstock/providers/tonghuashun.py
quickstock/services/__init__.py
quickstock/utils/__init__.py
quickstock/utils/code_converter.py
quickstock/utils/diagnostics.py
quickstock/utils/memory.py
quickstock/utils/migration.py
quickstock/utils/validators.py
quickstock-1.0.2.dist-info/licenses/LICENSE
quickstock-1.0.2.dist-info/METADATA
quickstock-1.0.2.dist-info/WHEEL
quickstock-1.0.2.dist-info/entry_points.txt
quickstock-1.0.2.dist-info/top_level.txt
quickstock-1.0.2.dist-info/RECORD
